{"Settings":{},"Property":{"m_ValidateChangesPrompt":{"Name":"Setting Change","Description":"-1","ClassName":"TParameterSelectData","Name History":[]},"m_CategoryList":{"Name":"Category List","Description":"-1","ClassName":"TParameterString","Name History":[]},"m_LogViewer":{"Name":"Log Viewer Style","Description":"Log Viewer Style","ClassName":"TParameterSelectData","Name History":[]}},"NotFile":{"m_Parameter":{"Name":"Service","Description":"Service","ClassName":"TParameter","Name History":[]},"m_QueueFilename":{"Name":"Queue Filename","Description":"Queue Filename","ClassName":"TParameterString","Name History":[]},"m_QueueSection":{"Name":"Queue Section","Description":"Queue Section","ClassName":"TParameterString","Name History":[]}}}
